evtk/__init__.py
pyevtk/__init__.py
pyevtk/_version.py
pyevtk/evtk.py
pyevtk/hl.py
pyevtk/vtk.py
pyevtk/xml.py
pyevtk-1.6.0.dist-info/LICENSE.txt
pyevtk-1.6.0.dist-info/METADATA
pyevtk-1.6.0.dist-info/WHEEL
pyevtk-1.6.0.dist-info/top_level.txt
pyevtk-1.6.0.dist-info/RECORD
