Metadata-Version: 2.1
Name: pyevtk
Version: 1.6.0
Summary: Export data as binary VTK files
Home-page: https://github.com/pyscience-projects/pyevtk
Author: Paulo Herrera
Author-email: pauloa.herrera@gmail.com
Maintainer: Adamos Kyriakou
Maintainer-email: somada141@gmail.com
Classifier: Programming Language :: Python :: 3.7
Classifier: Programming Language :: Python :: 3.8
Classifier: Programming Language :: Python :: 3.9
Classifier: Programming Language :: Python :: 3.10
Classifier: Programming Language :: Python :: 3.11
License-File: LICENSE.txt
